{
  "clans": [
    {
      "_id": { "$oid": "5f8d0d55b54764421b7156c1" },
      "nom": "Les Corsaires d'Armorique",
      "faction": "Corsaires",
      "total_points": 15000,
      "score_actuel": 4500,
      "couleur_hex": "#2563EB"
    },
    {
      "_id": { "$oid": "5f8d0d55b54764421b7156c2" },
      "nom": "Les Krakens de la Penfeld",
      "faction": "Krakens",
      "total_points": 13200,
      "score_actuel": 3800,
      "couleur_hex": "#DC2626"
    }
  ],
  "users": [
    {
      "_id": { "$oid": "5f8d0d55b54764421b715601" },
      "pseudo": "Lucas",
      "email": "lucas@example.com",
      "password": "hashed_password_123",
      "avatar": "🏴‍☠️",
      "wallet_points": 2500,
      "clan_id": { "$oid": "5f8d0d55b54764421b7156c1" },
      "inventory_cards": ["card_001", "card_005"]
    },
    {
      "_id": { "$oid": "5f8d0d55b54764421b715602" },
      "pseudo": "Martine",
      "email": "martine@example.com",
      "password": "hashed_password_123",
      "avatar": "🐙",
      "wallet_points": 3100,
      "clan_id": { "$oid": "5f8d0d55b54764421b7156c2" },
      "inventory_cards": ["card_010"]
    },
    {
      "_id": { "$oid": "5f8d0d55b54764421b715603" },
      "pseudo": "Thomas",
      "email": "thomas@example.com",
      "password": "hashed_password_123",
      "avatar": "⚓",
      "wallet_points": 1800,
      "clan_id": { "$oid": "5f8d0d55b54764421b7156c1" },
      "inventory_cards": []
    },
    {
      "_id": { "$oid": "5f8d0d55b54764421b715604" },
      "pseudo": "Sarah",
      "email": "sarah@example.com",
      "password": "hashed_password_123",
      "avatar": "🧜‍♀️",
      "wallet_points": 4200,
      "clan_id": { "$oid": "5f8d0d55b54764421b7156c2" },
      "inventory_cards": ["card_999", "card_777"]
    },
    {
      "_id": { "$oid": "5f8d0d55b54764421b715605" },
      "pseudo": "Erwan",
      "email": "erwan@example.com",
      "password": "hashed_password_123",
      "avatar": "🌊",
      "wallet_points": 500,
      "clan_id": { "$oid": "5f8d0d55b54764421b7156c1" },
      "inventory_cards": []
    }
  ],
  "events": [
    {
      "titre": "Opération Pneus au Port",
      "lat": 48.3831,
      "lon": -4.485,
      "type_dechet": "Pneus",
      "poids_estime": 50,
      "createur_id": { "$oid": "5f8d0d55b54764421b715601" },
      "est_valide": true
    },
    {
      "titre": "Nettoyage Plage du Moulin Blanc",
      "lat": 48.3912,
      "lon": -4.4375,
      "type_dechet": "Plastique",
      "poids_estime": 15,
      "createur_id": { "$oid": "5f8d0d55b54764421b715603" },
      "est_valide": true
    },
    {
      "titre": "Chasse aux mégots rue de Siam",
      "lat": 48.3885,
      "lon": -4.49,
      "type_dechet": "Mégots",
      "poids_estime": 2,
      "createur_id": { "$oid": "5f8d0d55b54764421b715602" },
      "est_valide": true
    },
    {
      "titre": "SOS Cannettes Recouvrance",
      "lat": 48.385,
      "lon": -4.498,
      "type_dechet": "Métal",
      "poids_estime": 5,
      "createur_id": { "$oid": "5f8d0d55b54764421b715604" },
      "est_valide": true
    },
    {
      "titre": "Plastiques Anse de Saint-Marc",
      "lat": 48.395,
      "lon": -4.45,
      "type_dechet": "Plastique",
      "poids_estime": 8,
      "createur_id": { "$oid": "5f8d0d55b54764421b715601" },
      "est_valide": false
    },
    {
      "titre": "Vieux filets Technopôle Plouzané",
      "lat": 48.358,
      "lon": -4.57,
      "type_dechet": "Filets de pêche",
      "poids_estime": 30,
      "createur_id": { "$oid": "5f8d0d55b54764421b715605" },
      "est_valide": true
    },
    {
      "titre": "Câbles abandonnés Pont Albert Louppe",
      "lat": 48.389,
      "lon": -4.395,
      "type_dechet": "Encombrants",
      "poids_estime": 20,
      "createur_id": { "$oid": "5f8d0d55b54764421b715602" },
      "est_valide": true
    },
    {
      "titre": "Bouteilles Parc d'Éole",
      "lat": 48.4,
      "lon": -4.51,
      "type_dechet": "Verre",
      "poids_estime": 10,
      "createur_id": { "$oid": "5f8d0d55b54764421b715603" },
      "est_valide": true
    },
    {
      "titre": "Cartons mouillés Capucins",
      "lat": 48.387,
      "lon": -4.495,
      "type_dechet": "Carton",
      "poids_estime": 4,
      "createur_id": { "$oid": "5f8d0d55b54764421b715601" },
      "est_valide": true
    },
    {
      "titre": "Déchets verts Vallon du Stang-Alar",
      "lat": 48.41,
      "lon": -4.44,
      "type_dechet": "Organique",
      "poids_estime": 12,
      "createur_id": { "$oid": "5f8d0d55b54764421b715604" },
      "est_valide": false
    }
  ]
}
